docuscospacy/__init__.py
docuscospacy/analyzers.py
docuscospacy/config.py
docuscospacy/corpus_analysis.py
docuscospacy/corpus_utils.py
docuscospacy/performance.py
docuscospacy/processors.py
docuscospacy/validation.py
docuscospacy/data/__init__.py
docuscospacy/data/micusp_mini.parquet
docuscospacy-0.3.6.dist-info/licenses/LICENSE
docuscospacy-0.3.6.dist-info/METADATA
docuscospacy-0.3.6.dist-info/WHEEL
docuscospacy-0.3.6.dist-info/top_level.txt
docuscospacy-0.3.6.dist-info/RECORD
