Metadata-Version: 2.4
Name: docuscospacy
Version: 0.3.6
Summary: Support for spaCy models trained on       DocuScope and the CLAWS7 tagset
Home-page: https://github.com/browndw/docuscospacy
Author: David Brown
Author-email: dwb2@andrew.cmu.edu
License: Apache License 2.0
Classifier: Development Status :: 4 - Beta
Classifier: Intended Audience :: Science/Research
Classifier: License :: OSI Approved :: Apache Software License
Classifier: Programming Language :: Python :: 3.10
Classifier: Programming Language :: Python :: 3.11
Classifier: Programming Language :: Python :: 3.12
Classifier: Topic :: Scientific/Engineering :: Information Analysis
Classifier: Topic :: Text Processing :: Linguistic
Requires-Python: >=3.10
License-File: LICENSE
Requires-Dist: importlib-resources>=6.5.0
Requires-Dist: polars>=1.30.0
Requires-Dist: spacy>=3.8.0
Requires-Dist: scipy>=1.10.0
Dynamic: author
Dynamic: author-email
Dynamic: classifier
Dynamic: description
Dynamic: description-content-type
Dynamic: home-page
Dynamic: license
Dynamic: license-file
Dynamic: requires-dist
Dynamic: requires-python
Dynamic: summary
